check_month/dsxz.py
check_month/sd.py
check_month/smonths.py
Calendar_Month_List_View-0.0.6.dist-info/METADATA
Calendar_Month_List_View-0.0.6.dist-info/WHEEL
Calendar_Month_List_View-0.0.6.dist-info/top_level.txt
Calendar_Month_List_View-0.0.6.dist-info/RECORD
