Metadata-Version: 2.1
Name: Calendar-Month-List-View
Version: 0.0.6
Summary: It generate month using current month value
Home-page: https://github.com/sathish48-codoid/Month-Generator-Using-Month-Value
Author: sathish
Author-email: samsathish48@gmail.com
License: UNKNOWN
Platform: UNKNOWN
Classifier: Programming Language :: Python :: 3
Classifier: License :: OSI Approved :: MIT License
Classifier: Operating System :: OS Independent
Requires-Python: >=3.6
